Metadata-Version: 2.1
Name: wordle-autosolver-lite
Version: 0.7.3
Summary: A Wordle solver that can generate optimal decision trees
Home-page: https://github.com/pueblak/wordle-autosolver-lite
Author: Kody Puebla
Author-email: pueblakody@gmail.com
License: GPL-3.0
Keywords: wordle,solve,solver,lite,optimize,optimal,best,dordle,quordle,octordle,duotrigordle,fibble,wordzy
Classifier: Programming Language :: Python :: 3.9
Classifier: License :: OSI Approved :: GNU General Public License v3 (GPLv3)
Classifier: Operating System :: OS Independent
Classifier: Environment :: Console
Classifier: Topic :: Games/Entertainment
Classifier: Natural Language :: English
Classifier: Development Status :: 4 - Beta
Requires-Python: >=3.9
License-File: LICENSE
Requires-Dist: tqdm
Provides-Extra: testing
Requires-Dist: flake8 (>=4.0) ; extra == 'testing'
Requires-Dist: tox (>=3.25) ; extra == 'testing'
Requires-Dist: pytest (>=7.1) ; extra == 'testing'
Requires-Dist: pytest-cov (>=3.0) ; extra == 'testing'
Requires-Dist: hypothesis (>=6.49) ; extra == 'testing'
